aitextgenAws/TokenDataset.py
aitextgenAws/__init__.py
aitextgenAws/aitextgenAws.py
aitextgenAws/cli.py
aitextgenAws/colab.py
aitextgenAws/tokenizers.py
aitextgenAws/train.py
aitextgenAws/utils.py
aitextgenAws/static/gpt2_merges.txt
aitextgenAws/static/gpt2_vocab.json
aitextgenAws-0.1.dist-info/LICENSE
aitextgenAws-0.1.dist-info/METADATA
aitextgenAws-0.1.dist-info/WHEEL
aitextgenAws-0.1.dist-info/entry_points.txt
aitextgenAws-0.1.dist-info/top_level.txt
aitextgenAws-0.1.dist-info/RECORD
