Metadata-Version: 2.1
Name: aitextgenAws
Version: 0.1
Summary: Fork of aitextgen to set parallel computing settings to be able to run on AWS sagemaker.
Home-page: https://github.com/cderinbogaz/aitextgen-aws
Author: Original work by Max Woolf, forked by Ceyhun Derinbogaz
Author-email: ceyhun@textcortex.com
License: MIT
Keywords: gpt-2,gpt2,text generation,ai
Platform: UNKNOWN
Requires-Python: >=3.6
Requires-Dist: transformers (>=4.5.1)
Requires-Dist: fire (>=0.3.0)
Requires-Dist: pytorch-lightning (>=1.2.7)
Requires-Dist: torch (>=1.6.0)
